{
  "settings": {
    "migrated": 6,
    "iconPacksPath": ".obsidian/icons",
    "fontSize": 16,
    "emojiStyle": "native",
    "iconColor": null,
    "recentlyUsedIcons": [
      "SiTestinglibrary",
      "SiApachemaven",
      "LiNetwork",
      "SiStreamrunners",
      "LiAppWindow"
    ],
    "recentlyUsedIconsSize": 5,
    "rules": [],
    "extraMargin": {
      "top": 0,
      "right": 4,
      "bottom": 0,
      "left": 0
    },
    "iconInTabsEnabled": false,
    "iconInTitleEnabled": false,
    "iconInTitlePosition": "above",
    "iconInFrontmatterEnabled": false,
    "iconInFrontmatterFieldName": "icon",
    "iconColorInFrontmatterFieldName": "iconColor",
    "iconsBackgroundCheckEnabled": false,
    "iconsInNotesEnabled": true,
    "iconsInLinksEnabled": true,
    "iconIdentifier": ":",
    "lucideIconPackType": "native",
    "debugMode": false
  },
  "AutomaçãoPython": {
    "iconName": "SiPython",
    "iconColor": "#fff829"
  },
  "Desafios": "LiActivity",
  "Diário": "LiBookOpenText",
  "HTML Para Visualização do Token No Email": {
    "iconName": "SiHtml5",
    "iconColor": "#292fd6"
  },
  "Imagens": "LiImage",
  "Java Collections": {
    "iconName": "LiCoffee",
    "iconColor": "#ffae00"
  },
  "Progamação Orientada a Objetos": "FarObjectGroup",
  "Sintaxe Básica Java": "LiAppWindow",
  "StreamAPI Java": "SiStreamrunners",
  "Work": "LiNetwork",
  "Maven": {
    "iconName": "SiApachemaven",
    "iconColor": "#ff0000"
  },
  "Teste de Software": "SiTestinglibrary"
}